.readthedocs.yaml
LICENSE.txt
MANIFEST
README.rst
increment_version.py
logo.png
logo.pxd
package_update_instructions.txt
requirements.txt
setup.cfg
setup.py
.vscode/settings.json
dist/verstack-0.1.0.tar.gz
docs/Doc_update_manual.txt
docs/Makefile
docs/make.bat
docs/requirements.txt
docs/build/doctrees/README.doctree
docs/build/doctrees/environment.pickle
docs/build/doctrees/index.doctree
docs/build/html/.buildinfo
docs/build/html/.nojekyll
docs/build/html/README.html
docs/build/html/genindex.html
docs/build/html/index.html
docs/build/html/objects.inv
docs/build/html/search.html
docs/build/html/searchindex.js
docs/build/html/_sources/README.md.txt
docs/build/html/_sources/README.rst.txt
docs/build/html/_sources/index.rst.txt
docs/build/html/_static/alabaster.css
docs/build/html/_static/basic.css
docs/build/html/_static/custom.css
docs/build/html/_static/doctools.js
docs/build/html/_static/documentation_options.js
docs/build/html/_static/file.png
docs/build/html/_static/guzzle.css
docs/build/html/_static/icon-example.png
docs/build/html/_static/icon-important.png
docs/build/html/_static/icon-javascript-example.png
docs/build/html/_static/icon-json-example.png
docs/build/html/_static/icon-lconf-example.png
docs/build/html/_static/icon-note.png
docs/build/html/_static/icon-optional.png
docs/build/html/_static/icon-python-example.png
docs/build/html/_static/icon-seealso.png
docs/build/html/_static/icon-shell-example.png
docs/build/html/_static/icon-text-example.png
docs/build/html/_static/icon-tip.png
docs/build/html/_static/icon-todo.png
docs/build/html/_static/icon-warning.png
docs/build/html/_static/jquery-3.4.1.js
docs/build/html/_static/jquery-3.5.1.js
docs/build/html/_static/jquery.cookie.js
docs/build/html/_static/jquery.js
docs/build/html/_static/jquery.min.map
docs/build/html/_static/language_data.js
docs/build/html/_static/local_fonts.css
docs/build/html/_static/minus.png
docs/build/html/_static/p_sphinx_theme.css
docs/build/html/_static/p_sphinx_theme.js
verstack.egg-info/PKG-INFO
verstack.egg-info/SOURCES.txt
verstack.egg-info/dependency_links.txt
verstack.egg-info/requires.txt
verstack.egg-info/top_level.txt
