Metadata-Version: 2.4
Name: verstack
Version: 4.3.8
Summary: Machine learning tools to make a Data Scientist's work more efficient
Home-page: https://github.com/DanilZherebtsov/verstack
Download-URL: https://github.com/DanilZherebtsov/verstack/archive/refs/tags/4.3.8.tar.gz
Author: Danil Zherebtsov
Author-email: danil.com@me.com
License: MIT
Keywords: impute,missing,values,stratify,nan,continuous,multiprocessing,concurrent,timer
Classifier: Development Status :: 4 - Beta
Classifier: Intended Audience :: Developers
Classifier: Topic :: Software Development :: Build Tools
Classifier: License :: OSI Approved :: MIT License
Classifier: Programming Language :: Python :: 3
Classifier: Programming Language :: Python :: 3.9
Classifier: Programming Language :: Python :: 3.10
Classifier: Programming Language :: Python :: 3.11
Classifier: Programming Language :: Python :: 3.12
License-File: LICENSE.txt
Requires-Dist: numpy~=2.3.1
Requires-Dist: pandas~=2.3.1
Requires-Dist: scikit-learn~=1.7.1
Requires-Dist: lightgbm~=4.5.0
Requires-Dist: optuna~=4.0.0
Requires-Dist: optuna-integration<=4.0.0,>=3.2.0
Requires-Dist: plotly~=5.24.0
Requires-Dist: matplotlib~=3.9.2
Requires-Dist: seaborn~=0.13.2
Requires-Dist: python-dateutil~=2.9.0
Requires-Dist: holidays~=0.56
Requires-Dist: mlxtend~=0.23.1
Requires-Dist: category_encoders~=2.8.1
Requires-Dist: tabulate~=0.9.0
Dynamic: author
Dynamic: author-email
Dynamic: classifier
Dynamic: description
Dynamic: description-content-type
Dynamic: download-url
Dynamic: home-page
Dynamic: keywords
Dynamic: license
Dynamic: license-file
Dynamic: requires-dist
Dynamic: summary
